graxpert/AstroImageRepository.py
graxpert/__init__.py
graxpert/ai_model_handling.py
graxpert/app_state.py
graxpert/astroimage.py
graxpert/background_extraction.py
graxpert/background_flood_selection.py
graxpert/background_grid_selection.py
graxpert/cmdline_tools.py
graxpert/commands.py
graxpert/deconvolution.py
graxpert/denoising.py
graxpert/grid_utils.py
graxpert/localization.py
graxpert/main.py
graxpert/mp_logging.py
graxpert/parallel_processing.py
graxpert/preferences.py
graxpert/progress.py
graxpert/radialbasisinterpolation.py
graxpert/resource_utils.py
graxpert/s3_secrets.py
graxpert/skyall.py
graxpert/stretch.py
graxpert/ui_scaling.py
graxpert/version.py
graxpert/application/__init__.py
graxpert/application/app.py
graxpert/application/app_events.py
graxpert/application/eventbus.py
graxpert/img/GraXpert_LOGO_Hauptvariante.png
graxpert/img/Icon.png
graxpert/img/LDN1235_original.jpg
graxpert/img/LDN1235_processed.jpg
graxpert/img/__init__.py
graxpert/img/gfx_numbers.png
graxpert/img/gfx_numbers.svg
graxpert/img/graXpert_Startbadge_Umbriel.png
graxpert/img/hourglass.png
graxpert/locales/__init__.py
graxpert/locales/de_DE/LC_MESSAGES/base.mo
graxpert/theme/__init__.py
graxpert/theme/graxpert-dark-blue.json
graxpert/ui/__init__.py
graxpert/ui/application_frame.py
graxpert/ui/canvas.py
graxpert/ui/left_menu.py
graxpert/ui/loadingframe.py
graxpert/ui/right_menu.py
graxpert/ui/statusbar.py
graxpert/ui/styling.py
graxpert/ui/tooltip.py
graxpert/ui/ui_events.py
graxpert/ui/widgets.py
graxpert-3.2.0a2.dist-info/METADATA
graxpert-3.2.0a2.dist-info/WHEEL
graxpert-3.2.0a2.dist-info/entry_points.txt
graxpert-3.2.0a2.dist-info/top_level.txt
graxpert-3.2.0a2.dist-info/RECORD
