Metadata-Version: 2.4
Name: graxpert
Version: 3.2.0a2
Summary: GraXpert is an astronomical image processing program for extracting and removing gradients in the background of your astrophotos
Home-page: https://graxpert.com
Author: GraXpert Development Team
Author-email: info@graxpert.com
License: GPL-3.0
Project-URL: Source Code, https://github.com/geeksville/GraXpert
Classifier: Development Status :: 3 - Alpha
Classifier: Intended Audience :: End Users/Desktop
Classifier: Intended Audience :: Science/Research
Classifier: Topic :: Scientific/Engineering :: Astronomy
Classifier: Topic :: Scientific/Engineering :: Image Processing
Classifier: Topic :: Multimedia :: Graphics :: Editors
Classifier: Programming Language :: Python :: 3.11
Classifier: Programming Language :: Python :: 3.12
Classifier: Programming Language :: Python :: 3.13
Classifier: Operating System :: Microsoft :: Windows
Classifier: Operating System :: MacOS
Classifier: Operating System :: POSIX :: Linux
Classifier: Environment :: Win32 (MS Windows)
Classifier: Environment :: MacOS X
Classifier: Environment :: X11 Applications
Classifier: Natural Language :: English
Classifier: Natural Language :: German
Requires-Python: >=3.11
Requires-Dist: ml-dtypes>=0.5.3
Requires-Dist: pillow>=11.3.0
Requires-Dist: appdirs
Requires-Dist: astropy>=6.0.1
Requires-Dist: astropy-iers-data>=0.2025.9.1.0.42.11
Requires-Dist: customtkinter>=5.2.2
Requires-Dist: imageio>=2.37.0
Requires-Dist: minio>=7.2.16
Requires-Dist: numpy<=2.2.6,>=2.0.2
Requires-Dist: opencv-python-headless==4.11.0.86
Requires-Dist: PyKrige>=1.7.2
Requires-Dist: requests>=2.32.5
Requires-Dist: scikit-image>=0.24.0
Requires-Dist: scipy>=1.13.1
Requires-Dist: xisf>=0.9.5
Provides-Extra: cuda
Requires-Dist: onnxruntime-gpu[cuda,cudnn]==1.22.0; extra == "cuda"
Provides-Extra: rocm
Requires-Dist: onnxruntime-rocm==1.22.1; extra == "rocm"
Provides-Extra: directml
Requires-Dist: onnxruntime-directml; extra == "directml"
Provides-Extra: openvino
Requires-Dist: onnxruntime-openvino==1.22.0; extra == "openvino"
Requires-Dist: openvino>=2025.3.0; extra == "openvino"
Provides-Extra: cpuonly
Requires-Dist: onnxruntime>=1.22.1; extra == "cpuonly"
Dynamic: author
Dynamic: author-email
Dynamic: classifier
Dynamic: description
Dynamic: description-content-type
Dynamic: home-page
Dynamic: license
Dynamic: project-url
Dynamic: provides-extra
Dynamic: requires-dist
Dynamic: requires-python
Dynamic: summary
